structlog_extras/__init__.py
structlog_extras/_proc.py
structlog_extras/presets.py
structlog_extras/py.typed
structlog_extras/stdlib.py
structlog_extras-0.6.0.dist-info/WHEEL
structlog_extras-0.6.0.dist-info/METADATA
structlog_extras-0.6.0.dist-info/RECORD
