Metadata-Version: 2.3
Name: structlog-extras
Version: 0.6.0
Summary: Various structlog additions, mainly focused on better stdlib integration
Keywords: logging,structlog
Author: Alexey Shokov
License: MIT
Classifier: Development Status :: 4 - Beta
Classifier: Programming Language :: Python :: 3.10
Classifier: Programming Language :: Python :: 3.11
Classifier: Programming Language :: Python :: 3.12
Classifier: Programming Language :: Python :: 3.13
Classifier: Programming Language :: Python :: 3.14
Classifier: Typing :: Typed
Classifier: Topic :: Software Development
Classifier: Intended Audience :: Developers
Classifier: License :: OSI Approved :: MIT License
Requires-Dist: structlog>=24.0
Requires-Python: >=3.10
Project-URL: Changelog, https://github.com/alexeyshockov/structlog-extras/blob/main/CHANGELOG.md
